myTokenize/Tokenizer.py
myTokenize/__init__.py
myTokenize/CRFTokenizer/wordseg_c2_crf.crfsuite
myTokenize/SentencePiece/bpe_sentencepiece_model.model
myTokenize/SentencePiece/bpe_sentencepiece_model.vocab
myTokenize/SentencePiece/unigram_sentencepiece_model.model
myTokenize/SentencePiece/unigram_sentencepiece_model.vocab
myTokenize/myWord/phrase_segment.py
myTokenize/myWord/word_segment.py
myTokenize/myWord/.ipynb_checkpoints/phrase_segment-checkpoint.py
myTokenize/myWord/.ipynb_checkpoints/word_segment-checkpoint.py
myTokenize-0.1.1.dist-info/LICENSE
myTokenize-0.1.1.dist-info/METADATA
myTokenize-0.1.1.dist-info/WHEEL
myTokenize-0.1.1.dist-info/top_level.txt
myTokenize-0.1.1.dist-info/RECORD
