Metadata-Version: 2.1
Name: myTokenize
Version: 0.1.1
Summary: Comprehensive tokenization library for Myanmar language
Home-page: https://github.com/ThuraAung1601/myTokenizer
Author: Ye Kyaw Thu, Thura Aung
Author-email: ykt.nlp.ai@gmail.com, thuraaung.ai.mdy@gmail.com
Classifier: Programming Language :: Python :: 3
Classifier: License :: OSI Approved :: MIT License
Classifier: Operating System :: OS Independent
Requires-Python: >=3.8
License-File: LICENSE
Requires-Dist: numpy
Requires-Dist: tensorflow==2.13
Requires-Dist: python-crfsuite
Requires-Dist: sentencepiece
Requires-Dist: matplotlib
Requires-Dist: GitPython
